paper_firehose/__init__.py
paper_firehose/cli.py
paper_firehose/commands/__init__.py
paper_firehose/commands/abstracts.py
paper_firehose/commands/email_list.py
paper_firehose/commands/export_recent.py
paper_firehose/commands/filter.py
paper_firehose/commands/generate_html.py
paper_firehose/commands/pqa_summary.py
paper_firehose/commands/rank.py
paper_firehose/core/__init__.py
paper_firehose/core/abstract_source.py
paper_firehose/core/command_context.py
paper_firehose/core/command_utils.py
paper_firehose/core/config.py
paper_firehose/core/database.py
paper_firehose/core/doi_utils.py
paper_firehose/core/http_client.py
paper_firehose/core/model_manager.py
paper_firehose/core/paths.py
paper_firehose/core/text_utils.py
paper_firehose/core/apis/__init__.py
paper_firehose/core/apis/crossref_client.py
paper_firehose/core/apis/openalex_client.py
paper_firehose/core/apis/pubmed_client.py
paper_firehose/core/apis/semantic_scholar_client.py
paper_firehose/processors/__init__.py
paper_firehose/processors/abstract_fetcher.py
paper_firehose/processors/emailer.py
paper_firehose/processors/feed_processor.py
paper_firehose/processors/html_generator.py
paper_firehose/processors/st_ranker.py
paper_firehose/system/config/config.yaml
paper_firehose/system/config/secrets/README.md
paper_firehose/system/config/secrets/mailing_lists.yaml
paper_firehose/system/config/topics/demo_topic.yaml
paper_firehose/system/templates/html_template.html
paper_firehose/system/templates/llmsummary_template.html
paper_firehose/system/templates/ranked_template.html
paper_firehose-0.2.17.dist-info/licenses/LICENSE
paper_firehose-0.2.17.dist-info/METADATA
paper_firehose-0.2.17.dist-info/WHEEL
paper_firehose-0.2.17.dist-info/entry_points.txt
paper_firehose-0.2.17.dist-info/top_level.txt
paper_firehose-0.2.17.dist-info/RECORD
