Metadata-Version: 2.4
Name: paper_firehose
Version: 0.2.17
Summary: Filter, rank, and summarize research-paper RSS feeds.
Author: Peter Nemes-Incze
License: MIT License
Keywords: rss,llm,research,papers,arxiv,summaries
Classifier: Intended Audience :: Science/Research
Classifier: License :: OSI Approved :: MIT License
Classifier: Operating System :: OS Independent
Classifier: Programming Language :: Python :: 3
Classifier: Programming Language :: Python :: 3.10
Classifier: Programming Language :: Python :: 3.11
Classifier: Programming Language :: Python :: 3.12
Classifier: Topic :: Scientific/Engineering :: Information Analysis
Requires-Python: >=3.10
License-File: LICENSE
Requires-Dist: feedparser
Requires-Dist: PyYAML
Requires-Dist: click
Requires-Dist: sentence-transformers>=2.2.2
Requires-Dist: requests
Requires-Dist: openai>=1.30.0
Requires-Dist: paper-qa
Requires-Dist: Pillow
Provides-Extra: dev
Requires-Dist: pytest>=7.0; extra == "dev"
Requires-Dist: pytest-cov; extra == "dev"
Provides-Extra: docs
Requires-Dist: sphinx>=7.3; extra == "docs"
Requires-Dist: sphinx-autodoc-typehints>=1.25; extra == "docs"
Requires-Dist: furo>=2024.1.29; extra == "docs"
Dynamic: license-file
